local_forex/__init__.py
local_forex/local_forex.py
local_forex/rate_data.json
local_forex-0.1.9.dist-info/LICENSE
local_forex-0.1.9.dist-info/METADATA
local_forex-0.1.9.dist-info/WHEEL
local_forex-0.1.9.dist-info/top_level.txt
local_forex-0.1.9.dist-info/RECORD
