Metadata-Version: 2.1
Name: local-forex
Version: 0.1.9
Summary: A package for maintaining and interacting with a local forex database.
Author: porkyc
Project-URL: Homepage, https://github.com/porkyc/local-forex
Classifier: Programming Language :: Python :: 3
Classifier: License :: OSI Approved :: MIT License
Classifier: Operating System :: OS Independent
Requires-Python: >=3.10
License-File: LICENSE
